tamer/__init__.py
tamer/cli.py
tamer/configs.py
tamer/utils.py
tamer-0.0.1.dist-info/METADATA
tamer-0.0.1.dist-info/WHEEL
tamer-0.0.1.dist-info/entry_points.txt
tamer-0.0.1.dist-info/licenses/LICENSE
tamer-0.0.1.dist-info/RECORD
